sestheta/__init__.py
sestheta-1.0.1.dist-info/LICENSE.txt
sestheta-1.0.1.dist-info/METADATA
sestheta-1.0.1.dist-info/WHEEL
sestheta-1.0.1.dist-info/top_level.txt
sestheta-1.0.1.dist-info/RECORD
